yaqg_ni/VERSION
yaqg_ni/__init__.py
yaqg_ni/__version__.py
yaqg_ni/_ni_daqmx_tmux_gui.py
yaqg_ni-2023.12.0.dist-info/entry_points.txt
yaqg_ni-2023.12.0.dist-info/LICENSE
yaqg_ni-2023.12.0.dist-info/WHEEL
yaqg_ni-2023.12.0.dist-info/METADATA
yaqg_ni-2023.12.0.dist-info/RECORD
