Metadata-Version: 2.1
Name: yaqg-ni
Version: 2023.12.0
Summary: qt-based gui for yaqd-ni daemons
Home-page: https://yaq.fyi
Author: Blaise Thompson
Author-email: blaise@untzag.com
Requires-Python: >=3.7
Classifier: Development Status :: 2 - Pre-Alpha
Classifier: Intended Audience :: Science/Research
Classifier: License :: OSI Approved :: GNU Lesser General Public License v3 (LGPLv3)
Classifier: Natural Language :: English
Classifier: Programming Language :: Python :: 3
Classifier: Programming Language :: Python :: 3.9
Classifier: Programming Language :: Python :: 3.10
Classifier: Programming Language :: Python :: 3.11
Classifier: Topic :: Scientific/Engineering
Requires-Dist: yaqc
Requires-Dist: pyqtgraph
Requires-Dist: qtypes
Requires-Dist: qtpy
Requires-Dist: numpy
Requires-Dist: tomli
Requires-Dist: black ; extra == "dev"
Requires-Dist: pre-commit ; extra == "dev"
Project-URL: Issues, https://github.com/yaq-project/yaqd-ni/issues
Project-URL: Source, https://github.com/yaq-project/yaqd-ni/
Provides-Extra: dev
